autodiffpy/__init__.py
autodiffpy/demo.py
autodiffpy/forward.py
autodiffpy/reverse.py
autodiffpy_free_holmes-0.0.9.dist-info/LICENSE
autodiffpy_free_holmes-0.0.9.dist-info/METADATA
autodiffpy_free_holmes-0.0.9.dist-info/WHEEL
autodiffpy_free_holmes-0.0.9.dist-info/top_level.txt
autodiffpy_free_holmes-0.0.9.dist-info/RECORD
