Metadata-Version: 2.1
Name: autodiffpy-free-holmes
Version: 0.0.9
Summary: UNKNOWN
Home-page: UNKNOWN
License: UNKNOWN
Platform: UNKNOWN
Requires-Dist: numpy
